CHANGES.rst
MANIFEST.in
README.rst
buildout.cfg
requirements.txt
setup.py
travis.cfg
docs/LICENSE.GPL
docs/LICENSE.txt
src/collective/__init__.py
src/collective.googleanalytics.egg-info/PKG-INFO
src/collective.googleanalytics.egg-info/SOURCES.txt
src/collective.googleanalytics.egg-info/dependency_links.txt
src/collective.googleanalytics.egg-info/entry_points.txt
src/collective.googleanalytics.egg-info/namespace_packages.txt
src/collective.googleanalytics.egg-info/not-zip-safe
src/collective.googleanalytics.egg-info/requires.txt
src/collective.googleanalytics.egg-info/top_level.txt
src/collective/googleanalytics/__init__.py
src/collective/googleanalytics/config.py
src/collective/googleanalytics/configure.zcml
src/collective/googleanalytics/doi18ndude
src/collective/googleanalytics/error.py
src/collective/googleanalytics/events.py
src/collective/googleanalytics/exportimport.py
src/collective/googleanalytics/loader.py
src/collective/googleanalytics/loader.tpl
src/collective/googleanalytics/loader.zcml
src/collective/googleanalytics/plugins.py
src/collective/googleanalytics/plugins.zcml
src/collective/googleanalytics/renderer.py
src/collective/googleanalytics/renderer.zcml
src/collective/googleanalytics/report.py
src/collective/googleanalytics/testing.py
src/collective/googleanalytics/upgrades.py
src/collective/googleanalytics/upgrades.zcml
src/collective/googleanalytics/utility.py
src/collective/googleanalytics/utils.py
src/collective/googleanalytics/visualization.py
src/collective/googleanalytics/visualization.tpl
src/collective/googleanalytics/vocabularies.py
src/collective/googleanalytics/browser/__init__.py
src/collective/googleanalytics/browser/analytics_config.js
src/collective/googleanalytics/browser/auth.py
src/collective/googleanalytics/browser/configure.zcml
src/collective/googleanalytics/browser/controlpanel.py
src/collective/googleanalytics/browser/controlpanel_layout.pt
src/collective/googleanalytics/browser/report.py
src/collective/googleanalytics/browser/images/chart_bar.gif
src/collective/googleanalytics/browser/images/chart_curve.gif
src/collective/googleanalytics/browser/images/loading.gif
src/collective/googleanalytics/interfaces/__init__.py
src/collective/googleanalytics/interfaces/browserlayer.py
src/collective/googleanalytics/interfaces/loader.py
src/collective/googleanalytics/interfaces/plugins.py
src/collective/googleanalytics/interfaces/report.py
