Metadata-Version: 1.1
Name: collective.googleanalytics
Version: 1.6.1
Summary: Tools for pulling statistics from Google Analytics.
Home-page: https://github.com/collective/collective.googleanalytics
Author: Matt Yoder
Author-email: mattyoder@groundwire.org
License: GPL
Keywords: Google Analytics Plone statistics portlet integration
Platform: UNKNOWN
Classifier: Development Status :: 5 - Production/Stable
Classifier: Framework :: Plone
Classifier: Framework :: Plone :: 4.3
Classifier: Framework :: Plone :: 5.0
Classifier: Framework :: Plone :: 5.1
Classifier: Intended Audience :: System Administrators
Classifier: License :: OSI Approved :: GNU General Public License (GPL)
Classifier: Operating System :: OS Independent
Classifier: Programming Language :: JavaScript
Classifier: Programming Language :: Python
Classifier: Programming Language :: Python :: 2.7
Classifier: Topic :: Internet :: Log Analysis
Classifier: Topic :: Internet :: WWW/HTTP :: Site Management
Classifier: Topic :: Software Development :: Libraries :: Python Modules
